gazelleapi/__init__.py
gazelleapi/gazelleapi.py
gazelleapi-0.1.2.dist-info/DESCRIPTION.rst
gazelleapi-0.1.2.dist-info/METADATA
gazelleapi-0.1.2.dist-info/RECORD
gazelleapi-0.1.2.dist-info/WHEEL
gazelleapi-0.1.2.dist-info/metadata.json
gazelleapi-0.1.2.dist-info/top_level.txt
gazelleapi-0.1.2.dist-info/zip-safe
