Metadata-Version: 2.0
Name: gazelleapi
Version: 0.1.2
Summary: Gazelle API
Home-page: https://github.com/itismadness/gazelleapi
Author: itismadness
Author-email: it.is.madness@gmail.com
License: MIT
Platform: UNKNOWN
Classifier: Development Status :: 5 - Production/Stable
Classifier: Intended Audience :: Developers
Classifier: License :: OSI Approved :: MIT License
Classifier: Natural Language :: English
Classifier: Operating System :: OS Independent
Classifier: Programming Language :: Python
Classifier: Programming Language :: Python :: 2.7
Classifier: Programming Language :: Python :: 3
Requires-Dist: future
Requires-Dist: requests
